diswebing.py
diswebing-0.0.4.dist-info/LICENSE
diswebing-0.0.4.dist-info/METADATA
diswebing-0.0.4.dist-info/WHEEL
diswebing-0.0.4.dist-info/top_level.txt
diswebing-0.0.4.dist-info/RECORD
