Metadata-Version: 2.1
Name: diswebing
Version: 0.0.4
Summary: 간단하게 보낼수있는 웹훅
Home-page: UNKNOWN
Author: Martin Bodický
Author-email: 
License: UNKNOWN
Platform: UNKNOWN
Classifier: Development Status :: 3 - Alpha
Classifier: License :: OSI Approved :: MIT License
Classifier: Operating System :: OS Independent
Classifier: Programming Language :: Python :: 3
Classifier: Programming Language :: Python :: 3.8
License-File: LICENSE
Requires-Dist: requests (~=2.25.1)
